<lcgdict>
  <class name="sbn::RangeP" ClassVersion="10">
   <version ClassVersion="10" checksum="75193157"/>
  </class>
  <class name="std::vector<sbn::RangeP>" />
  <class name="art::Wrapper<sbn::RangeP>" />
  <class name="art::Wrapper<std::vector<sbn::RangeP>>" />

  <class name="art::Assns<sbn::RangeP, recob::Track, void>" />
  <class name="art::Wrapper<art::Assns<sbn::RangeP, recob::Track, void>>" />

  <class name="art::Assns<recob::Track, sbn::RangeP, void>" />
  <class name="art::Wrapper<art::Assns<recob::Track, sbn::RangeP, void>>" />

  <class name="art::Assns<recob::Track, recob::MCSFitResult, void>" />
  <class name="art::Wrapper<art::Assns<recob::Track, recob::MCSFitResult, void>>" />
  <class name="art::Assns<recob::MCSFitResult, recob::Track, void>" />
  <class name="art::Wrapper<art::Assns<recob::MCSFitResult, recob::Track, void>>" />

  <class name="sbn::FlashTriggerPrimitive::Trig" ClassVersion="10">
   <version ClassVersion="10" checksum="571406659"/>
  </class>
  <class name="art::Wrapper<sbn::FlashTriggerPrimitive::Trig>" />
  <class name="std::vector<sbn::FlashTriggerPrimitive::Trig>" />
  <class name="art::Wrapper<std::vector<sbn::FlashTriggerPrimitive::Trig>>" />

  <class name="sbn::FlashTriggerPrimitive" ClassVersion="10">
   <version ClassVersion="10" checksum="459565667"/>
  </class>
  <class name="art::Wrapper<sbn::FlashTriggerPrimitive>" />
  <class name="std::vector<sbn::FlashTriggerPrimitive>" />
  <class name="art::Wrapper<std::vector<sbn::FlashTriggerPrimitive>>" />

  <class name="sbn::SimpleFlashMatch" ClassVersion="11">
   <version ClassVersion="11" checksum="27328003"/>
  </class>
  <class name="sbn::SimpleFlashMatch::Charge" ClassVersion="11">
   <version ClassVersion="11" checksum="4057441913"/>
  </class>
  <class name="sbn::SimpleFlashMatch::Flash" ClassVersion="11">
   <version ClassVersion="11" checksum="3396465673"/>
  </class>
  <class name="sbn::SimpleFlashMatch::Score" ClassVersion="11">
   <version ClassVersion="11" checksum="3697420401"/>
  </class>
  <class name="std::vector<sbn::SimpleFlashMatch>" />
  <class name="art::Wrapper<sbn::SimpleFlashMatch>" />
  <class name="art::Wrapper<std::vector<sbn::SimpleFlashMatch>>" />
  <class name="art::Assns<recob::PFParticle, sbn::SimpleFlashMatch>" />
  <class name="art::Wrapper<art::Assns<recob::PFParticle, sbn::SimpleFlashMatch>>" />
  <class name="art::Assns<sbn::SimpleFlashMatch,recob::PFParticle, void>" />
  <class name="art::Wrapper<art::Assns<sbn::SimpleFlashMatch, recob::PFParticle, void> >" />

  <class name="sbn::CRUMBSResult" ClassVersion="10">
   <version ClassVersion="10" checksum="1001500335"/>
  </class>
  <class name="std::vector<sbn::CRUMBSResult>" />
  <class name="art::Wrapper<sbn::CRUMBSResult>" />
  <class name="art::Wrapper<std::vector<sbn::CRUMBSResult>>" />
  <class name="art::Assns<recob::Slice, sbn::CRUMBSResult>" />
  <class name="art::Wrapper<art::Assns<recob::Slice, sbn::CRUMBSResult>>" />
  <class name="art::Assns<sbn::CRUMBSResult,recob::Slice, void>" />
  <class name="art::Wrapper<art::Assns<sbn::CRUMBSResult, recob::Slice, void> >" />

  <class name="art::Assns<recob::Track, sbn::crt::CRTHit, anab::T0>" />
  <class name="art::Wrapper<art::Assns<recob::Track, sbn::crt::CRTHit, anab::T0>>" />
  <class name="art::Assns<recob::Track, sbn::crt::CRTHit, void>" />
  <class name="art::Wrapper<art::Assns<recob::Track, sbn::crt::CRTHit, void>>" />

  <class name="art::Assns<sbn::crt::CRTHit, recob::Track, anab::T0>" />
  <class name="art::Wrapper<art::Assns<sbn::crt::CRTHit, recob::Track, anab::T0>>" />
  <class name="art::Assns<sbn::crt::CRTHit, recob::Track, void>" />
  <class name="art::Wrapper<art::Assns<sbn::crt::CRTHit, recob::Track, void>>" />

  <class name="sbn::ShowerDensityFit" ClassVersion="10">
   <version ClassVersion="10" checksum="942453570"/>
  </class>
  <class name="std::vector<sbn::ShowerDensityFit>" />
  <class name="art::Wrapper<sbn::ShowerDensityFit>" />
  <class name="art::Wrapper<std::vector<sbn::ShowerDensityFit>>" />

  <class name="art::Assns<recob::Shower, sbn::ShowerDensityFit, void>" />
  <class name="art::Wrapper<art::Assns<recob::Shower, sbn::ShowerDensityFit, void>>" />

  <class name="art::Assns<sbn::ShowerDensityFit, recob::Shower, void>" />
  <class name="art::Wrapper<art::Assns<sbn::ShowerDensityFit, recob::Shower, void>>" />

  <class name="sbn::ShowerTrackFit" ClassVersion="10">
   <version ClassVersion="10" checksum="3197274838"/>
  </class>
  <class name="std::vector<sbn::ShowerTrackFit>" />
  <class name="art::Wrapper<sbn::ShowerTrackFit>" />
  <class name="art::Wrapper<std::vector<sbn::ShowerTrackFit>>" />

  <class name="art::Assns<recob::Shower, sbn::ShowerTrackFit, void>" />
  <class name="art::Wrapper<art::Assns<recob::Shower, sbn::ShowerTrackFit, void>>" />

  <class name="art::Assns<sbn::ShowerTrackFit, recob::Shower, void>" />
  <class name="art::Wrapper<art::Assns<sbn::ShowerTrackFit, recob::Shower, void>>" />

  <class name="art::Assns<float,recob::Shower,void>" />
  <class name="art::Assns<recob::Shower,float,void>" />
  <class name="art::Wrapper<art::Assns<float,recob::Shower,void>>" />
  <class name="art::Wrapper<art::Assns<recob::Shower,float,void>>" />

  <class name="sbn::Stub" ClassVersion="13">
   <version ClassVersion="13" checksum="3533111376"/>
   <version ClassVersion="12" checksum="1338933861"/>
   <version ClassVersion="11" checksum="1552964364"/>
   <version ClassVersion="10" checksum="3948825604"/>
  </class>
  <class name="std::vector<sbn::Stub>" />
  <class name="art::Wrapper<sbn::Stub>" />
  <class name="art::Wrapper<std::vector<sbn::Stub>>" />

  <class name="sbn::StubHit"/>
  <class name="std::vector<sbn::StubHit>" />
  <class name="std::vector<std::vector<sbn::StubHit>>" />
  <class name="art::Wrapper<sbn::StubHit>" />
  <class name="art::Wrapper<std::vector<sbn::StubHit>>" />

  <class name="art::Assns<recob::PFParticle, sbn::Stub>" />
  <class name="art::Wrapper<art::Assns<recob::PFParticle, sbn::Stub>>" />
  <class name="art::Assns<sbn::Stub, recob::PFParticle, void>" />
  <class name="art::Wrapper<art::Assns<sbn::Stub, recob::PFParticle, void>>" />
  <class name="art::Assns<recob::Slice, sbn::Stub>" />
  <class name="art::Wrapper<art::Assns<recob::Slice, sbn::Stub>>" />
  <class name="art::Assns<sbn::Stub, recob::Slice, void>" />
  <class name="art::Wrapper<art::Assns<sbn::Stub, recob::Slice, void>>" />
  <class name="art::Assns<recob::Hit, sbn::Stub>" />
  <class name="art::Wrapper<art::Assns<recob::Hit, sbn::Stub>>" />
  <class name="art::Assns<sbn::Stub, recob::Hit, void>" />
  <class name="art::Wrapper<art::Assns<sbn::Stub, recob::Hit, void>>" />
  <class name="art::Assns<sbn::VertexHit, sbn::Stub>" />
  <class name="art::Wrapper<art::Assns<sbn::VertexHit, sbn::Stub>>" />
  <class name="art::Assns<sbn::Stub, sbn::VertexHit, void>" />
  <class name="art::Wrapper<art::Assns<sbn::Stub, sbn::VertexHit, void>>" />

  <class name="sbn::VertexHit" ClassVersion="13">
   <version ClassVersion="13" checksum="4209046416"/>
   <version ClassVersion="12" checksum="1155278781"/>
   <version ClassVersion="11" checksum="4130374952"/>
   <version ClassVersion="10" checksum="802899277"/>
  </class>
  <class name="std::vector<sbn::VertexHit>" />
  <class name="art::Wrapper<sbn::VertexHit>" />
  <class name="art::Wrapper<std::vector<sbn::VertexHit>>" />

  <class name="art::Assns<recob::Hit, sbn::VertexHit>" />
  <class name="art::Wrapper<art::Assns<recob::Hit, sbn::VertexHit>>" />
  <class name="art::Assns<sbn::VertexHit, recob::Hit, void>" />
  <class name="art::Wrapper<art::Assns<sbn::VertexHit, recob::Hit, void>>" />
  <class name="art::Assns<recob::Slice, sbn::VertexHit>" />
  <class name="art::Wrapper<art::Assns<recob::Slice, sbn::VertexHit>>" />
  <class name="art::Assns<sbn::VertexHit, recob::Slice, void>" />
  <class name="art::Wrapper<art::Assns<sbn::VertexHit, recob::Slice, void>>" />
  <class name="art::Assns<recob::Vertex, sbn::VertexHit>" />
  <class name="art::Wrapper<art::Assns<recob::Vertex, sbn::VertexHit>>" />
  <class name="art::Assns<sbn::VertexHit, recob::Vertex, void>" />
  <class name="art::Wrapper<art::Assns<sbn::VertexHit, recob::Vertex, void>>" />

  <class name="sbn::MergedTrackInfo" ClassVersion="11">
   <version ClassVersion="11" checksum="72646431"/>
   <version ClassVersion="10" checksum="252455777"/>
  </class>
  <class name="std::vector<sbn::MergedTrackInfo>" />
  <class name="art::Wrapper<sbn::MergedTrackInfo>" />
  <class name="art::Wrapper<std::vector<sbn::MergedTrackInfo>>" />

  <class name="art::Assns<recob::PFParticle, sbn::MergedTrackInfo>" />
  <class name="art::Wrapper<art::Assns<recob::PFParticle, sbn::MergedTrackInfo>>" />
  <class name="art::Assns<recob::Track, sbn::MergedTrackInfo>" />
  <class name="art::Wrapper<art::Assns<recob::Track, sbn::MergedTrackInfo>>" />
  <class name="art::Assns<recob::PFParticle, recob::Track, sbn::MergedTrackInfo>" />
  <class name="art::Wrapper<art::Assns<recob::PFParticle, recob::Track, sbn::MergedTrackInfo>>" />

  <class name="sbn::StoppingChi2Fit" ClassVersion="11">
   <version ClassVersion="11" checksum="577431198"/>
  </class>
  <class name="std::vector<sbn::StoppingChi2Fit>" />
  <class name="art::Wrapper<sbn::StoppingChi2Fit>" />
  <class name="art::Wrapper<std::vector<sbn::StoppingChi2Fit>>" />

  <class name="art::Assns<recob::Track, sbn::StoppingChi2Fit>" />
  <class name="art::Assns<anab::Calorimetry, sbn::StoppingChi2Fit>" />
  <class name="art::Wrapper<art::Assns<recob::Track, sbn::StoppingChi2Fit>>" />
  <class name="art::Wrapper<art::Assns<anab::Calorimetry, sbn::StoppingChi2Fit>>" />

  <class name="art::Assns<sbn::StoppingChi2Fit, recob::Track>" />
  <class name="art::Assns<sbn::StoppingChi2Fit, anab::Calorimetry>" />
  <class name="art::Wrapper<art::Assns<sbn::StoppingChi2Fit, recob::Track>>" />
  <class name="art::Wrapper<art::Assns<sbn::StoppingChi2Fit, anab::Calorimetry>>" />

  <class name="sbn::ScatterClosestApproach" ClassVersion="11">
   <version ClassVersion="11" checksum="2117354105"/>
  </class>
  <class name="std::vector<sbn::ScatterClosestApproach>" />
  <class name="art::Wrapper<sbn::ScatterClosestApproach>" />
  <class name="art::Wrapper<std::vector<sbn::ScatterClosestApproach>>" />

  <class name="art::Assns<recob::Track, sbn::ScatterClosestApproach>" />
  <class name="art::Wrapper<art::Assns<recob::Track, sbn::ScatterClosestApproach>>" />

  <class name="art::Assns<sbn::ScatterClosestApproach, recob::Track>" />
  <class name="art::Wrapper<art::Assns<sbn::ScatterClosestApproach, recob::Track>>" />

  <class name="std::map<int, float> "/>
  <class name="sbn::MVAPID" ClassVersion="11">
   <version ClassVersion="11" checksum="442803767"/>
  </class>
  <class name="std::vector<sbn::MVAPID>" />
  <class name="art::Wrapper<sbn::MVAPID>" />
  <class name="art::Wrapper<std::vector<sbn::MVAPID>>" />

  <class name="art::Assns<recob::Track, sbn::MVAPID>" />
  <class name="art::Assns<recob::Shower, sbn::MVAPID>" />
  <class name="art::Assns<recob::PFParticle, sbn::MVAPID>" />
  <class name="art::Wrapper<art::Assns<recob::Track, sbn::MVAPID>>" />
  <class name="art::Wrapper<art::Assns<recob::Shower, sbn::MVAPID>>" />
  <class name="art::Wrapper<art::Assns<recob::PFParticle, recob::Track, sbn::MVAPID>>" />

  <class name="art::Assns<sbn::MVAPID, recob::Track>" />
  <class name="art::Assns<sbn::MVAPID, recob::Shower>" />
  <class name="art::Assns<sbn::MVAPID, recob::PFParticle>" />
  <class name="art::Wrapper<art::Assns<sbn::MVAPID, recob::Track>>" />
  <class name="art::Wrapper<art::Assns<sbn::MVAPID, recob::Shower>>" />
  <class name="art::Wrapper<art::Assns<sbn::MVAPID, recob::PFParticle, recob::Track>>" />

  <class name="std::vector<geo::PlaneID>"/>
</lcgdict>
